vxparser/__init__.py
vxparser/__main__.py
vxparser/api.py
vxparser/cli.py
vxparser/helper/epg/lib/__init__.py
vxparser/helper/epg/lib/channel_selector.py
vxparser/helper/epg/lib/filesplit.py
vxparser/helper/epg/lib/mapper.py
vxparser/helper/epg/lib/xml_structure.py
vxparser/helper/epg/providers/horizon.py
vxparser/helper/epg/providers/magenta_DE.py
vxparser/helper/epg/providers/swisscom_CH.py
vxparser/helper/epg/providers/tvspielfilm_DE.py
vxparser/helper/epg/providers/zattoo.py
vxparser/helper/epg/service.py
vxparser/helper/epg/settings.py
vxparser/helper/iptv.py
vxparser/helper/requestHandler.py
vxparser/helper/resolveurl/__init__.py
vxparser/helper/resolveurl/common.py
vxparser/helper/resolveurl/data/addon.xml
vxparser/helper/resolveurl/data/changelog.txt
vxparser/helper/resolveurl/data/fanart.jpg
vxparser/helper/resolveurl/data/icon.png
vxparser/helper/resolveurl/data/resources/images/DialogBack1.png
vxparser/helper/resolveurl/data/resources/images/DialogBack2.png
vxparser/helper/resolveurl/data/resources/images/border90.png
vxparser/helper/resolveurl/data/resources/images/checked.png
vxparser/helper/resolveurl/data/resources/images/greeninch.png
vxparser/helper/resolveurl/data/resources/images/redx.png
vxparser/helper/resolveurl/data/resources/language/resource.language.cs_cz/strings.po
vxparser/helper/resolveurl/data/resources/language/resource.language.de_de/strings.po
vxparser/helper/resolveurl/data/resources/language/resource.language.el_gr/strings.po
vxparser/helper/resolveurl/data/resources/language/resource.language.en_gb/strings.po
vxparser/helper/resolveurl/data/resources/language/resource.language.en_us/strings.po
vxparser/helper/resolveurl/data/resources/language/resource.language.es_es/strings.po
vxparser/helper/resolveurl/data/resources/language/resource.language.gl_es/strings.po
vxparser/helper/resolveurl/data/resources/language/resource.language.hr_hr/strings.po
vxparser-1.4.8.post1.dist-info/LICENSE
vxparser-1.4.8.post1.dist-info/METADATA
vxparser-1.4.8.post1.dist-info/WHEEL
vxparser-1.4.8.post1.dist-info/entry_points.txt
vxparser-1.4.8.post1.dist-info/RECORD
