Metadata-Version: 2.3
Name: vxparser
Version: 1.4.8.post1
Summary: FastApi Server backend for VAVOO Live TV & German, to publish it via Xtream Code api.
Author: Mastaaa
Author-email: sebastianspaaa@gmail.com
Requires-Python: >=3.8
Classifier: Programming Language :: Python :: 3
Classifier: Programming Language :: Python :: 3.8
Classifier: Programming Language :: Python :: 3.9
Classifier: Programming Language :: Python :: 3.10
Classifier: Programming Language :: Python :: 3.11
Classifier: Programming Language :: Python :: 3.12
Classifier: Programming Language :: Python :: 3.13
Requires-Dist: aiohttp (>=3.8.1)
Requires-Dist: fastapi (>=0.95.0)
Requires-Dist: inquirer (>=3.1.3)
Requires-Dist: python-multipart (>=0.0.6)
Requires-Dist: requests (>=2.31.0)
Requires-Dist: six (>=1.16.0)
Requires-Dist: unidecode (>=1.3.7)
Requires-Dist: uvicorn (>=0.13.3)
